BaseDT/BaseData.py
BaseDT/BaseDataSet.py
BaseDT/BaseIO.py
BaseDT/BasePlot.py
BaseDT/__init__.py
BaseDT/data.py
BaseDT/data_image.py
BaseDT/dataset.py
BaseDT/io.py
BaseDT/plot.py
BaseDT/utils.py
BaseDT/version.py
BaseDT-0.1.3.dist-info/METADATA
BaseDT-0.1.3.dist-info/WHEEL
BaseDT-0.1.3.dist-info/entry_points.txt
BaseDT-0.1.3.dist-info/top_level.txt
BaseDT-0.1.3.dist-info/zip-safe
BaseDT-0.1.3.dist-info/RECORD
