Metadata-Version: 2.1
Name: BaseDT
Version: 0.1.3
Summary: BaseDT is a data-processing  tool including data, dataset, io and plot.
Home-page: https://github.com/OpenXLab-Edu/OpenMMLab-Edu
Author: OpenXLab
Author-email: wangbolun@pjlab.org.cn
License: MIT License
Platform: UNKNOWN
Requires-Python: >=3.6
Requires-Dist: opencv-python (>=4.1.2.30)
Requires-Dist: numpy
Requires-Dist: scikit-learn
